elbat/__init__.py
elbat/commands/analyze.py
elbat/commands/config.py
elbat/commands/diag.py
elbat/commands/disco.py
elbat/commands/offload.py
elbat/commands/present.py
elbat/main.py
elbat/workflows/base.py
elbat-0.1.1.dist-info/entry_points.txt
elbat-0.1.1.dist-info/WHEEL
elbat-0.1.1.dist-info/METADATA
elbat-0.1.1.dist-info/RECORD
