Metadata-Version: 2.1
Name: elbat
Version: 0.1.1
Summary: 
Author: Cody Fincher
Author-email: cody@gluent.com
Requires-Python: >=3.7,<4
Classifier: Programming Language :: Python :: 3
Classifier: Programming Language :: Python :: 3.7
Classifier: Programming Language :: Python :: 3.8
Classifier: Programming Language :: Python :: 3.9
Classifier: Programming Language :: Python :: 3.10
Requires-Dist: SQLAlchemy (>=1.4.22,<2.0.0)
Requires-Dist: click-help-colors (>=0.9.1,<0.10.0)
Requires-Dist: cx-Oracle (>=8.2.1,<9.0.0)
Requires-Dist: importlib-metadata (>=1.0,<2.0); python_version < "3.8"
Requires-Dist: loguru (>=0.5.3,<0.6.0)
Requires-Dist: typer[all] (>=0.3.2,<0.4.0)
